setup.py
wayround_org/gsasl/Makefile.py
wayround_org/gsasl/__init__.py
wayround_org/gsasl/gsasl.pyx
wayround_org/gsasl/gsasl_h.pxd
wayround_org_gsasl.egg-info/PKG-INFO
wayround_org_gsasl.egg-info/SOURCES.txt
wayround_org_gsasl.egg-info/dependency_links.txt
wayround_org_gsasl.egg-info/top_level.txt