Metadata-Version: 1.0
Name: wayround-org-gsasl
Version: 0.2.1
Summary: Python gsasl binding
Home-page: UNKNOWN
Author: UNKNOWN
Author-email: UNKNOWN
License: UNKNOWN
Platform: UNKNOWN
